pyhub/__init__.py
pyhub/__main__.py
pyhub/caches.py
pyhub/config.py
pyhub/http.py
pyhub/init.py
pyhub/logger.py
pyhub/routers.py
pyhub/versions.py
pyhub/core/__init__.py
pyhub/core/apps.py
pyhub/core/toml_utils.py
pyhub/core/utils.py
pyhub/core/commands/__init__.py
pyhub/core/models/__init__.py
pyhub/core/models/fields.py
pyhub/core/static/pyhub/markdown.js
pyhub/core/static/pyhub/alpinejs/3.14.8/cdn.min.js
pyhub/core/static/pyhub/htmx/2.0.4/htmx.min.js
pyhub/core/static/pyhub/htmx-ext/README.md
pyhub/core/static/pyhub/htmx-ext/streaming-html.js
pyhub/core/static/pyhub/htmx-ext/sse/2.2.2/sse.js
pyhub/core/static/pyhub/htmx-ext/ws/register.js
pyhub/core/static/pyhub/htmx-ext/ws/2.0.1/ws.js
pyhub/core/static/pyhub/marked/15.0.7/.editorconfig
pyhub/core/static/pyhub/marked/15.0.7/.gitattributes
pyhub/core/static/pyhub/marked/15.0.7/.gitignore
pyhub/core/static/pyhub/marked/15.0.7/.releaserc.json
pyhub/core/static/pyhub/marked/15.0.7/marked.cjs
pyhub/core/static/pyhub/marked/15.0.7/marked.cjs.map
pyhub/core/static/pyhub/marked/15.0.7/marked.d.cts
pyhub/core/static/pyhub/marked/15.0.7/marked.d.ts
pyhub/core/static/pyhub/marked/15.0.7/marked.esm.js
pyhub/core/static/pyhub/marked/15.0.7/marked.esm.js.map
pyhub/core/static/pyhub/marked/15.0.7/marked.umd.js
pyhub/core/static/pyhub/marked/15.0.7/marked.umd.js.map
pyhub/core/static/pyhub/marked/15.0.7/.devcontainer/devcontainer.json
pyhub/core/static/pyhub/marked/15.0.7/.github/ISSUE_TEMPLATE.md
pyhub/core/static/pyhub/marked/15.0.7/.github/PULL_REQUEST_TEMPLATE.md
pyhub/core/static/pyhub/marked/15.0.7/.github/dependabot.yml
pyhub/core/static/pyhub/marked/15.0.7/.github/ISSUE_TEMPLATE/Bug_report.md
pyhub/core/static/pyhub/marked/15.0.7/.github/ISSUE_TEMPLATE/Feature_request.md
pyhub/core/static/pyhub/marked/15.0.7/.github/ISSUE_TEMPLATE/Proposal.md
pyhub/core/static/pyhub/marked/15.0.7/.github/PULL_REQUEST_TEMPLATE/badges.md
pyhub/core/static/pyhub/marked/15.0.7/.github/workflows/tests.yml
django_pyhub_rag-1.4.0.dist-info/METADATA
django_pyhub_rag-1.4.0.dist-info/WHEEL
django_pyhub_rag-1.4.0.dist-info/entry_points.txt
django_pyhub_rag-1.4.0.dist-info/RECORD
