Metadata-Version: 2.4
Name: django-pyhub-rag
Version: 1.4.0
Summary: Django app library for RAG integration
Project-URL: Homepage, https://github.com/pyhub-kr/django-pyhub-rag
Project-URL: Documentation, https://rag.pyhub.kr
Project-URL: Repository, https://github.com/pyhub-kr/django-pyhub-rag
Project-URL: Issues, https://github.com/pyhub-kr/django-pyhub-rag/issues
Author-email: Chinseok Lee <me@pyhub.kr>
License: MIT
Classifier: Development Status :: 4 - Beta
Classifier: Framework :: Django
Classifier: Intended Audience :: Developers
Classifier: License :: OSI Approved :: MIT License
Classifier: Operating System :: OS Independent
Classifier: Programming Language :: Python
Classifier: Programming Language :: Python :: 3
Classifier: Programming Language :: Python :: 3.10
Classifier: Programming Language :: Python :: 3.11
Classifier: Programming Language :: Python :: 3.12
Classifier: Programming Language :: Python :: 3.13
Classifier: Topic :: Software Development :: Libraries :: Python Modules
Requires-Python: >=3.10
Requires-Dist: anthropic
Requires-Dist: colorlog
Requires-Dist: cotton-heroicons
Requires-Dist: crispy-tailwind
Requires-Dist: django-components
Requires-Dist: django-cotton
Requires-Dist: django-crispy-forms
Requires-Dist: django-debug-toolbar
Requires-Dist: django-environ
Requires-Dist: django-extensions
Requires-Dist: django-htmx
Requires-Dist: django-lifecycle
Requires-Dist: django-rich
Requires-Dist: django-template-partials
Requires-Dist: django-typer[rich]
Requires-Dist: django>=4.0.0
Requires-Dist: google-genai
Requires-Dist: httpx
Requires-Dist: ollama
Requires-Dist: openai
Requires-Dist: pillow
Requires-Dist: rich
Requires-Dist: tiktoken
Requires-Dist: toml
Requires-Dist: typer
Provides-Extra: all
Requires-Dist: django-shinobi; extra == 'all'
Requires-Dist: mcp; extra == 'all'
Requires-Dist: numpy; extra == 'all'
Requires-Dist: pgvector; extra == 'all'
Requires-Dist: psycopg2-binary; extra == 'all'
Requires-Dist: pycryptodome; extra == 'all'
Requires-Dist: pypdf2; extra == 'all'
Requires-Dist: sqlite-vec; extra == 'all'
Requires-Dist: uvicorn; extra == 'all'
Provides-Extra: build
Requires-Dist: build; extra == 'build'
Requires-Dist: setuptools; extra == 'build'
Requires-Dist: twine; extra == 'build'
Requires-Dist: wheel; extra == 'build'
Provides-Extra: dev
Requires-Dist: black; extra == 'dev'
Requires-Dist: djlint; extra == 'dev'
Requires-Dist: isort; extra == 'dev'
Requires-Dist: pre-commit; extra == 'dev'
Requires-Dist: ruff; extra == 'dev'
Provides-Extra: docs
Requires-Dist: mkdocs; extra == 'docs'
Requires-Dist: mkdocs-glightbox; extra == 'docs'
Requires-Dist: mkdocs-material; extra == 'docs'
Requires-Dist: pymdown-extensions; extra == 'docs'
Provides-Extra: mcp
Requires-Dist: mcp; extra == 'mcp'
Provides-Extra: parser
Requires-Dist: pycryptodome; extra == 'parser'
Requires-Dist: pypdf2; extra == 'parser'
Provides-Extra: postgres
Requires-Dist: pgvector; extra == 'postgres'
Requires-Dist: psycopg2-binary; extra == 'postgres'
Provides-Extra: sqlite
Requires-Dist: numpy; extra == 'sqlite'
Requires-Dist: sqlite-vec; extra == 'sqlite'
Provides-Extra: test
Requires-Dist: pytest; extra == 'test'
Requires-Dist: pytest-asyncio; extra == 'test'
Requires-Dist: pytest-django; extra == 'test'
Requires-Dist: pytest-testdox; extra == 'test'
Provides-Extra: web
Requires-Dist: django-shinobi; extra == 'web'
Requires-Dist: uvicorn; extra == 'web'
